odoo10_addon_business_requirement_deliverable_project-10.0.1.0.0-py2.7-nspkg.pth
odoo/addons/business_requirement_deliverable_project/README.rst
odoo/addons/business_requirement_deliverable_project/__init__.py
odoo/addons/business_requirement_deliverable_project/__manifest__.py
odoo/addons/business_requirement_deliverable_project/i18n/sl.po
odoo/addons/business_requirement_deliverable_project/models/__init__.py
odoo/addons/business_requirement_deliverable_project/models/business.py
odoo/addons/business_requirement_deliverable_project/models/project.py
odoo/addons/business_requirement_deliverable_project/static/description/icon.png
odoo/addons/business_requirement_deliverable_project/static/img/bus_req_project.png
odoo/addons/business_requirement_deliverable_project/tests/__init__.py
odoo/addons/business_requirement_deliverable_project/tests/test_br.py
odoo/addons/business_requirement_deliverable_project/views/business_view.xml
odoo/addons/business_requirement_deliverable_project/views/project.xml
odoo/addons/business_requirement_deliverable_project/wizard/__init__.py
odoo/addons/business_requirement_deliverable_project/wizard/generate_projects.py
odoo/addons/business_requirement_deliverable_project/wizard/generate_projects_view.xml
odoo10_addon_business_requirement_deliverable_project-10.0.1.0.0.dist-info/DESCRIPTION.rst
odoo10_addon_business_requirement_deliverable_project-10.0.1.0.0.dist-info/METADATA
odoo10_addon_business_requirement_deliverable_project-10.0.1.0.0.dist-info/RECORD
odoo10_addon_business_requirement_deliverable_project-10.0.1.0.0.dist-info/WHEEL
odoo10_addon_business_requirement_deliverable_project-10.0.1.0.0.dist-info/metadata.json
odoo10_addon_business_requirement_deliverable_project-10.0.1.0.0.dist-info/namespace_packages.txt
odoo10_addon_business_requirement_deliverable_project-10.0.1.0.0.dist-info/top_level.txt
