Metadata-Version: 2.0
Name: odoo10-addon-business-requirement-deliverable-project
Version: 10.0.1.0.0
Summary: Create projects and tasks directly from the Business Requirement and Resources lines
Home-page: https://www.elico-corp.com/
Author: Elico Corp, Odoo Community Association (OCA)
Author-email: support@odoo-community.org
License: AGPL-3
Platform: UNKNOWN
Classifier: Programming Language :: Python
Classifier: Framework :: Odoo
Classifier: License :: OSI Approved :: GNU Affero General Public License v3
Requires-Python: ~=2.7
Requires-Dist: odoo (<10.1dev,>=10.0)
Requires-Dist: odoo10-addon-business-requirement-deliverable
Requires-Dist: odoo10-addon-project-parent
